loess/CHANGELOG.rst
loess/LICENSE.txt
loess/README.rst
loess/__init__.py
loess/loess_1d.py
loess/loess_2d.py
loess/examples/__init__.py
loess/examples/loess_1d_example.py
loess/examples/loess_2d_example.py
loess-2.1.2.dist-info/METADATA
loess-2.1.2.dist-info/WHEEL
loess-2.1.2.dist-info/top_level.txt
loess-2.1.2.dist-info/zip-safe
loess-2.1.2.dist-info/RECORD
