Metadata-Version: 2.1
Name: loess
Version: 2.1.2
Summary: LOESS: smoothing via robust locally-weighted regression in one or two dimensions
Home-page: https://purl.org/cappellari/software
Author: Michele Cappellari
Author-email: michele.cappellari@physics.ox.ac.uk
License: Other/Proprietary License
Classifier: Development Status :: 5 - Production/Stable
Classifier: Intended Audience :: Developers
Classifier: Intended Audience :: Science/Research
Classifier: Operating System :: OS Independent
Classifier: Programming Language :: Python :: 3
Requires-Dist: numpy
Requires-Dist: matplotlib
Requires-Dist: plotbin
